janus/__init__.py
janus/janus.py
janus_python-0.1.0.dist-info/METADATA
janus_python-0.1.0.dist-info/WHEEL
janus_python-0.1.0.dist-info/top_level.txt
janus_python-0.1.0.dist-info/RECORD
