Metadata-Version: 2.4
Name: janus-python
Version: 0.1.0
Summary: Track and Verify LLM Actions
Author-email: Jet Wu <jet@withjanus.com>
Project-URL: Homepage, https://github.com/jw-source/janus-python
Project-URL: Repository, https://github.com/jw-source/janus-python
Project-URL: Issues, https://github.com/jw-source/janus-python/issues
Requires-Python: >=3.7
Requires-Dist: requests>=2.20.0
Requires-Dist: psutil>=5.6.0
